atrest/__init__.py
atrest/api.py
atrest/client.py
atrest/config.py
atrest/test/__init__.py
atrest/test/test_api.py
src/client.py
atrest-1.0.2.dist-info/METADATA
atrest-1.0.2.dist-info/WHEEL
atrest-1.0.2.dist-info/top_level.txt
atrest-1.0.2.dist-info/RECORD
