Metadata-Version: 2.1
Name: atrest
Version: 1.0.2
Summary: Basic Autotask REST Client
Home-page: UNKNOWN
Author: Jonathan Weaver
Author-email: createchange@protonmail.com
License: UNKNOWN
Platform: UNKNOWN
Classifier: Programming Language :: Python :: 3
Requires-Dist: requests
